main.py
oarslily-0.1.2.dist-info/licenses/LICENSE
oarslily-0.1.2.dist-info/METADATA
oarslily-0.1.2.dist-info/WHEEL
oarslily-0.1.2.dist-info/entry_points.txt
oarslily-0.1.2.dist-info/top_level.txt
oarslily-0.1.2.dist-info/RECORD
