Metadata-Version: 2.4
Name: oarslily
Version: 0.1.2
Summary: Add your description here
License: MIT
Requires-Python: >=3.13
License-File: LICENSE
Requires-Dist: osslili>=1.6.1
Requires-Dist: python-levenshtein>=0.27.3
Requires-Dist: python-tlsh>=4.5.0
Dynamic: license-file
